namegeneratormodule/__init__.py
namegeneratormodule/database.py
namegeneratormodule/inserting.py
namegeneratormodule/main.py
namegeneratormodule/name.py
namegeneratormodule-0.0.3.dist-info/METADATA
namegeneratormodule-0.0.3.dist-info/WHEEL
namegeneratormodule-0.0.3.dist-info/top_level.txt
namegeneratormodule-0.0.3.dist-info/RECORD
