Metadata-Version: 2.1
Name: namegeneratormodule
Version: 0.0.3
Summary: Random Name Generator
Home-page: UNKNOWN
Author: Nuke
Author-email: rochadcmarcos@gmail.com
License: UNKNOWN
Keywords: python,first packages
Platform: UNKNOWN
Classifier: Development Status :: 3 - Alpha
Classifier: Intended Audience :: Education
Classifier: Programming Language :: Python :: 2
Classifier: Programming Language :: Python :: 3
Classifier: Operating System :: MacOS :: MacOS X
Classifier: Operating System :: Microsoft :: Windows
